datascienv/__init__.py
datascienv/datascienv.py
datascienv-0.1.2.dist-info/LICENSE
datascienv-0.1.2.dist-info/METADATA
datascienv-0.1.2.dist-info/WHEEL
datascienv-0.1.2.dist-info/top_level.txt
datascienv-0.1.2.dist-info/zip-safe
datascienv-0.1.2.dist-info/RECORD
