Metadata-Version: 2.1
Name: datascienv
Version: 0.1.2
Summary: Data Science package for setup data science environment in single line
Home-page: http://github.com/ashishpatel26/datascienv
Author: ashishpatel26
Author-email: ashishpatel.ce.2011@gmail.com
License: UNKNOWN
Keywords: Datascienv,Data Science installation in single line,data science,datascience,datasci,datascience environment
Platform: any
Classifier: License :: OSI Approved :: MIT License
Classifier: Programming Language :: Python :: 3
Requires-Dist: pandas
Requires-Dist: numpy
Requires-Dist: scipy
Requires-Dist: matplotlib
Requires-Dist: seaborn
Requires-Dist: scikit-learn
Requires-Dist: statsmodels
Requires-Dist: pyforest
Requires-Dist: pycaret
Requires-Dist: Flask
Requires-Dist: fastapi
Requires-Dist: jupyter
Requires-Dist: xgboost
Requires-Dist: imbalanced-learn
Requires-Dist: bokeh
Requires-Dist: kat
Requires-Dist: Boruta
Requires-Dist: spyder
Requires-Dist: mlxtend
Requires-Dist: lightgbm
Requires-Dist: catboost
Requires-Dist: tensorflow-cpu (==2.6.0)
Requires-Dist: tensorflow-gpu (==2.6.0)
